welkin/__init__.py
welkin/__version__.py
welkin/authentication.py
welkin/client.py
welkin/exceptions.py
welkin/models/__init__.py
welkin/models/assessment.py
welkin/models/base.py
welkin/models/calendar.py
welkin/models/care_plan.py
welkin/models/cdt.py
welkin/models/chat.py
welkin/models/document.py
welkin/models/email.py
welkin/models/encounter.py
welkin/models/export.py
welkin/models/formation.py
welkin/models/patient.py
welkin/models/program.py
welkin/models/sms.py
welkin/models/user.py
welkin/pagination.py
welkin/util.py
welkin-0.1.6.dist-info/LICENSE.md
welkin-0.1.6.dist-info/METADATA
welkin-0.1.6.dist-info/WHEEL
welkin-0.1.6.dist-info/RECORD
