Metadata-Version: 2.1
Name: welkin
Version: 0.1.6
Summary: Python Welkin Health API Wrapper.
Home-page: https://github.com/lightmatter/welkin-health
License: GPL-3.0-or-later
Author: Sam Morgan
Author-email: sama4mail@gmail.com
Requires-Python: >=3.8,<4.0
Classifier: Intended Audience :: Developers
Classifier: License :: OSI Approved :: GNU General Public License v3 (GPLv3)
Classifier: License :: OSI Approved :: GNU General Public License v3 or later (GPLv3+)
Classifier: Operating System :: OS Independent
Classifier: Programming Language :: Python :: 3
Classifier: Programming Language :: Python :: 3.8
Classifier: Programming Language :: Python :: 3.9
Classifier: Programming Language :: Python :: 3.10
Classifier: Programming Language :: Python :: 3.11
Classifier: Programming Language :: Python :: 3.12
Requires-Dist: inflection (>=0.5.1,<0.6.0)
Requires-Dist: portalocker (>=2.8.2,<3.0.0)
Requires-Dist: requests (>=2.31.0,<3.0.0)
Project-URL: Bug Tracker, https://github.com/lightmatter/welkin-health/issues
Project-URL: Documentation, https://welkin.readthedocs.io
Project-URL: Repository, https://github.com/lightmatter/welkin-health
